[
{
  "id":"0001",
  "blogtitle":"我的第一篇博客文章",
  "blogtime":"2020-5-27",
  "blogtype":"tech",
  "blogsubtitle":"1.我的第一篇博客",
  "blogtags":"JS"
},
{
  "id":"0002",
  "blogtitle":"jQuery基础笔记",
  "blogtime":"2020-5-28",
  "blogtype":"tech",
  "blogsubtitle":"jQuery基础学习笔记",
  "blogtags":"jQuery"
},
{
  "id":"0003",
  "blogtitle":"原生Js运动框架笔记",
  "blogtime":"2020-5-28",
  "blogtype":"tech",
  "blogsubtitle":"原生运动框架",
  "blogtags":"JS"
},
{
  "id":"0004",
  "blogtitle":"豆瓣首页项目笔记",
  "blogtime":"2020-5-28",
  "blogtype":"tech",
  "blogsubtitle":"豆瓣首页踩坑实录",
  "blogtags":"JS CSS HTML"
},
{
  "id":"0005",
  "blogtitle":"css块级格式化上下文笔记",
  "blogtime":"2020-5-28",
  "blogtype":"tech",
  "blogsubtitle":"BFC块级格式化上下文",
  "blogtags":"CSS"
},
{
  "id":"0006",
  "blogtitle":"王小波语录",
  "blogtime":"2020-5-28",
  "blogtype":"life",
  "blogsubtitle":"王小波语录",
  "blogtags":"Life"
},
{
  "id":"0007",
  "blogtitle":"个人博客第一阶段总结",
  "blogtime":"2020-5-29",
  "blogtype":"tech",
  "blogsubtitle":"博客总结",
  "blogtags":"JS"
},
{
  "id":"0008",
  "blogtitle":"部署服务器nginx403报错",
  "blogtime":"2020-6-4",
  "blogtype":"tech",
  "blogsubtitle":"部署服务器nginx",
  "blogtags":"服务器"
},
{
  "id":"0009",
  "blogtitle":"Flex布局总结",
  "blogtime":"2020-6-9",
  "blogtype":"tech",
  "blogsubtitle":"Flex弹性盒常用总结",
  "blogtags":"CSS"
},
{
  "id":"0010",
  "blogtitle":"Grid布局总结",
  "blogtime":"2020-6-9",
  "blogtype":"tech",
  "blogsubtitle":"Grid栅格常用总结",
  "blogtags":"CSS"
},
{
  "id":"0011",
  "blogtitle":"CSS变形透视动画",
  "blogtime":"2020-6-10",
  "blogtype":"tech",
  "blogsubtitle":"变形透视动画总结",
  "blogtags":"CSS"
},
{
  "id":"0012",
  "blogtitle":"trisition动画过渡",
  "blogtime":"2020-6-10",
  "blogtype":"tech",
  "blogsubtitle":"动画过渡总结",
  "blogtags":"CSS"
},
{
  "id":"0013",
  "blogtitle":"animation动画",
  "blogtime":"2020-6-11",
  "blogtype":"tech",
  "blogsubtitle":"animation动画总结",
  "blogtags":"CSS"
},
{
  "id":"0014",
  "blogtitle":"3",
  "blogtime":"2020-8-8",
  "blogtype":"life",
  "blogsubtitle":"3",
  "blogtags":"Life"
},
{
  "id":"0015",
  "blogtitle":"闭包",
  "blogtime":"2020-8-8",
  "blogtype":"tech",
  "blogsubtitle":"闭包相关",
  "blogtags":"高频面试"
},
{
  "id":"0016",
  "blogtitle":"栈内存与堆内存",
  "blogtime":"2020-8-8",
  "blogtype":"tech",
  "blogsubtitle":"栈与堆",
  "blogtags":"高频面试"
},
{
  "id":"0017",
  "blogtitle":"立即执行函数",
  "blogtime":"2020-8-9",
  "blogtype":"tech",
  "blogsubtitle":"立即执行函数知识点",
  "blogtags":"高频面试"
},
{
  "id":"0018",
  "blogtitle":"性能优化",
  "blogtime":"2020-8-9",
  "blogtype":"tech",
  "blogsubtitle":"性能优化方式",
  "blogtags":"高频面试"
},
{
  "id":"0019",
  "blogtitle":"深浅拷贝",
  "blogtime":"2020-8-9",
  "blogtype":"tech",
  "blogsubtitle":"深浅拷贝实现",
  "blogtags":"高频面试"
},
{
  "id":"0020",
  "blogtitle":"原型与原型链",
  "blogtime":"2020-8-10",
  "blogtype":"tech",
  "blogsubtitle":"原型与原型链总结与练习",
  "blogtags":"高频面试"
},
{
  "id":"0021",
  "blogtitle":"Vuex总结",
  "blogtime":"2020-8-10",
  "blogtype":"tech",
  "blogsubtitle":"Vuex",
  "blogtags":"Vue"
},
{
  "id":"0022",
  "blogtitle":"Vue生命周期",
  "blogtime":"2020-8-10",
  "blogtype":"tech",
  "blogsubtitle":"生命周期",
  "blogtags":"Vue"
},
{
  "id":"0023",
  "blogtitle":"ES6异步编程与Promise",
  "blogtime":"2020-8-10",
  "blogtype":"tech",
  "blogsubtitle":"异步与Promise",
  "blogtags":"ES6"
}
]